authflow/__init__.py
authflow/authflow.py
authflow/main.py
authflow/api/__init__.py
authflow/api/audit.py
authflow/api/auth.py
authflow/api/dependencies.py
authflow/api/gdpr.py
authflow/api/mfa.py
authflow/api/organizations.py
authflow/api/roles.py
authflow/api/teams.py
authflow/api/users.py
authflow/core/__init__.py
authflow/core/audit.py
authflow/core/config.py
authflow/core/default_roles.py
authflow/core/exceptions.py
authflow/core/initialization.py
authflow/core/jwt_handler.py
authflow/core/permissions.py
authflow/core/provider.py
authflow/middleware/__init__.py
authflow/middleware/auth.py
authflow/models/__init__.py
authflow/models/audit.py
authflow/models/schemas.py
authflow/providers/__init__.py
authflow/providers/keycloak.py
authflow/scripts/__init__.py
authflow/scripts/seed_test_users.py
authflow/utils/__init__.py
authflow/utils/keycloak_admin.py
authflow-0.4.0.dist-info/METADATA
authflow-0.4.0.dist-info/WHEEL
authflow-0.4.0.dist-info/entry_points.txt
authflow-0.4.0.dist-info/top_level.txt
authflow-0.4.0.dist-info/RECORD
