Metadata-Version: 2.4
Name: authflow
Version: 0.4.0
Summary: Highly configurable authentication and authorization package wrapping Keycloak
Author: AuthFlow Contributors
License: MIT
Project-URL: Homepage, https://github.com/authflow/authflow-stack
Project-URL: Documentation, https://authflow.readthedocs.io
Project-URL: Repository, https://github.com/authflow/authflow-stack
Project-URL: Issues, https://github.com/authflow/authflow-stack/issues
Keywords: authentication,authorization,keycloak,fastapi,rbac,multi-tenant
Classifier: Development Status :: 3 - Alpha
Classifier: Intended Audience :: Developers
Classifier: License :: OSI Approved :: MIT License
Classifier: Programming Language :: Python :: 3
Classifier: Programming Language :: Python :: 3.11
Classifier: Programming Language :: Python :: 3.12
Classifier: Framework :: FastAPI
Classifier: Topic :: Security
Classifier: Topic :: Software Development :: Libraries :: Python Modules
Requires-Python: >=3.11
Requires-Dist: fastapi==0.115.9
Requires-Dist: pydantic>=2.0.0
Requires-Dist: pydantic[email]>=2.0.0
Requires-Dist: pydantic-settings>=2.0.0
Requires-Dist: python-keycloak>=3.9.0
Requires-Dist: pyjwt[crypto]>=2.8.0
Requires-Dist: redis>=5.0.0
Requires-Dist: httpx>=0.27.0
Requires-Dist: pyyaml>=6.0.0
Requires-Dist: python-multipart>=0.0.6
Requires-Dist: uvicorn[standard]>=0.27.0
Provides-Extra: dev
Requires-Dist: pytest>=8.0.0; extra == "dev"
Requires-Dist: pytest-asyncio>=0.23.0; extra == "dev"
Requires-Dist: pytest-cov>=4.1.0; extra == "dev"
Requires-Dist: black>=24.0.0; extra == "dev"
Requires-Dist: ruff>=0.2.0; extra == "dev"
Requires-Dist: mypy>=1.8.0; extra == "dev"
Requires-Dist: pre-commit>=3.6.0; extra == "dev"
Provides-Extra: build
Requires-Dist: build>=1.0.0; extra == "build"
Requires-Dist: twine>=4.0.0; extra == "build"
